[
  {
    "ContainingType": "BlazorCARS.HealthShield.WebAPI.Controllers.AuthController",
    "Method": "LoginAsync",
    "RelativePath": "api/auth/login",
    "HttpMethod": "POST",
    "IsController": true,
    "Order": 0,
    "Parameters": [
      {
        "Name": "userStoreDTO",
        "Type": "BlazorCARS.HealthShield.DataObject.DTO.UserDTO",
        "IsRequired": true
      }
    ],
    "ReturnTypes": [
      {
        "Type": "BlazorCARS.HealthShield.Utility.Response.APIResponse",
        "MediaTypes": [
          "text/plain",
          "application/json",
          "text/json"
        ],
        "StatusCode": 200
      },
      {
        "Type": "Microsoft.AspNetCore.Mvc.ProblemDetails",
        "MediaTypes": [
          "text/plain",
          "application/json",
          "text/json"
        ],
        "StatusCode": 400
      }
    ]
  },
  {
    "ContainingType": "BlazorCARS.HealthShield.WebAPI.Controllers.CountryController",
    "Method": "GetAllAsync",
    "RelativePath": "api/countries",
    "HttpMethod": "GET",
    "IsController": true,
    "Order": 0,
    "Parameters": [
      {
        "Name": "pageSize",
        "Type": "System.Int32",
        "IsRequired": false
      },
      {
        "Name": "pageNumber",
        "Type": "System.Int32",
        "IsRequired": false
      }
    ],
    "ReturnTypes": [
      {
        "Type": "BlazorCARS.HealthShield.Utility.Response.APIResponse",
        "MediaTypes": [
          "text/plain",
          "application/json",
          "text/json"
        ],
        "StatusCode": 200
      },
      {
        "Type": "Microsoft.AspNetCore.Mvc.ProblemDetails",
        "MediaTypes": [
          "text/plain",
          "application/json",
          "text/json"
        ],
        "StatusCode": 400
      },
      {
        "Type": "System.Void",
        "MediaTypes": [],
        "StatusCode": 500
      },
      {
        "Type": "Microsoft.AspNetCore.Mvc.ProblemDetails",
        "MediaTypes": [
          "text/plain",
          "application/json",
          "text/json"
        ],
        "StatusCode": 401
      }
    ]
  },
  {
    "ContainingType": "BlazorCARS.HealthShield.WebAPI.Controllers.CountryController",
    "Method": "CreateAsync",
    "RelativePath": "api/countries",
    "HttpMethod": "POST",
    "IsController": true,
    "Order": 0,
    "Parameters": [
      {
        "Name": "requestDTO",
        "Type": "BlazorCARS.HealthShield.DataObject.DTO.CountryCreateDTO",
        "IsRequired": true
      }
    ],
    "ReturnTypes": [
      {
        "Type": "BlazorCARS.HealthShield.Utility.Response.APIResponse",
        "MediaTypes": [
          "text/plain",
          "application/json",
          "text/json"
        ],
        "StatusCode": 201
      },
      {
        "Type": "Microsoft.AspNetCore.Mvc.ProblemDetails",
        "MediaTypes": [
          "text/plain",
          "application/json",
          "text/json"
        ],
        "StatusCode": 400
      },
      {
        "Type": "System.Void",
        "MediaTypes": [],
        "StatusCode": 500
      }
    ]
  },
  {
    "ContainingType": "BlazorCARS.HealthShield.WebAPI.Controllers.CountryController",
    "Method": "GetByIdAsync",
    "RelativePath": "api/countries/{id}",
    "HttpMethod": "GET",
    "IsController": true,
    "Order": 0,
    "Parameters": [
      {
        "Name": "id",
        "Type": "System.Int32",
        "IsRequired": true
      }
    ],
    "ReturnTypes": [
      {
        "Type": "Microsoft.AspNetCore.Mvc.ProblemDetails",
        "MediaTypes": [
          "text/plain",
          "application/json",
          "text/json"
        ],
        "StatusCode": 400
      },
      {
        "Type": "Microsoft.AspNetCore.Mvc.ProblemDetails",
        "MediaTypes": [
          "text/plain",
          "application/json",
          "text/json"
        ],
        "StatusCode": 404
      },
      {
        "Type": "BlazorCARS.HealthShield.Utility.Response.APIResponse",
        "MediaTypes": [
          "text/plain",
          "application/json",
          "text/json"
        ],
        "StatusCode": 200
      },
      {
        "Type": "System.Void",
        "MediaTypes": [],
        "StatusCode": 500
      }
    ]
  },
  {
    "ContainingType": "BlazorCARS.HealthShield.WebAPI.Controllers.CountryController",
    "Method": "UpdateAsync",
    "RelativePath": "api/countries/{id}",
    "HttpMethod": "PUT",
    "IsController": true,
    "Order": 0,
    "Parameters": [
      {
        "Name": "id",
        "Type": "System.Int32",
        "IsRequired": true
      },
      {
        "Name": "requestDTO",
        "Type": "BlazorCARS.HealthShield.DataObject.DTO.CountryUpdateDTO",
        "IsRequired": true
      }
    ],
    "ReturnTypes": [
      {
        "Type": "BlazorCARS.HealthShield.Utility.Response.APIResponse",
        "MediaTypes": [
          "text/plain",
          "application/json",
          "text/json"
        ],
        "StatusCode": 200
      },
      {
        "Type": "Microsoft.AspNetCore.Mvc.ProblemDetails",
        "MediaTypes": [
          "text/plain",
          "application/json",
          "text/json"
        ],
        "StatusCode": 404
      },
      {
        "Type": "System.Void",
        "MediaTypes": [],
        "StatusCode": 500
      },
      {
        "Type": "Microsoft.AspNetCore.Mvc.ProblemDetails",
        "MediaTypes": [
          "text/plain",
          "application/json",
          "text/json"
        ],
        "StatusCode": 400
      }
    ]
  },
  {
    "ContainingType": "BlazorCARS.HealthShield.WebAPI.Controllers.CountryController",
    "Method": "DeleteAync",
    "RelativePath": "api/countries/{id}/{DeletedUser}",
    "HttpMethod": "DELETE",
    "IsController": true,
    "Order": 0,
    "Parameters": [
      {
        "Name": "id",
        "Type": "System.Int32",
        "IsRequired": true
      },
      {
        "Name": "DeletedUser",
        "Type": "System.String",
        "IsRequired": true
      }
    ],
    "ReturnTypes": [
      {
        "Type": "System.Void",
        "MediaTypes": [],
        "StatusCode": 500
      },
      {
        "Type": "Microsoft.AspNetCore.Mvc.ProblemDetails",
        "MediaTypes": [
          "text/plain",
          "application/json",
          "text/json"
        ],
        "StatusCode": 400
      },
      {
        "Type": "System.Void",
        "MediaTypes": [],
        "StatusCode": 204
      },
      {
        "Type": "Microsoft.AspNetCore.Mvc.ProblemDetails",
        "MediaTypes": [
          "text/plain",
          "application/json",
          "text/json"
        ],
        "StatusCode": 404
      }
    ]
  },
  {
    "ContainingType": "BlazorCARS.HealthShield.WebAPI.Controllers.HospitalRegistryController",
    "Method": "CreateAsync",
    "RelativePath": "api/hospitalRegistry",
    "HttpMethod": "POST",
    "IsController": true,
    "Order": 0,
    "Parameters": [
      {
        "Name": "requestDTO",
        "Type": "BlazorCARS.HealthShield.DataObject.DTO.HospitalRegistryDTO",
        "IsRequired": true
      }
    ],
    "ReturnTypes": [
      {
        "Type": "BlazorCARS.HealthShield.Utility.Response.APIResponse",
        "MediaTypes": [
          "text/plain",
          "application/json",
          "text/json"
        ],
        "StatusCode": 201
      },
      {
        "Type": "Microsoft.AspNetCore.Mvc.ProblemDetails",
        "MediaTypes": [
          "text/plain",
          "application/json",
          "text/json"
        ],
        "StatusCode": 400
      },
      {
        "Type": "System.Void",
        "MediaTypes": [],
        "StatusCode": 500
      }
    ]
  },
  {
    "ContainingType": "BlazorCARS.HealthShield.WebAPI.Controllers.HospitalController",
    "Method": "GetAllAsync",
    "RelativePath": "api/hospitals",
    "HttpMethod": "GET",
    "IsController": true,
    "Order": 0,
    "Parameters": [
      {
        "Name": "pageSize",
        "Type": "System.Int32",
        "IsRequired": false
      },
      {
        "Name": "pageNumber",
        "Type": "System.Int32",
        "IsRequired": false
      }
    ],
    "ReturnTypes": [
      {
        "Type": "BlazorCARS.HealthShield.Utility.Response.APIResponse",
        "MediaTypes": [
          "text/plain",
          "application/json",
          "text/json"
        ],
        "StatusCode": 200
      },
      {
        "Type": "Microsoft.AspNetCore.Mvc.ProblemDetails",
        "MediaTypes": [
          "text/plain",
          "application/json",
          "text/json"
        ],
        "StatusCode": 400
      },
      {
        "Type": "System.Void",
        "MediaTypes": [],
        "StatusCode": 500
      },
      {
        "Type": "Microsoft.AspNetCore.Mvc.ProblemDetails",
        "MediaTypes": [
          "text/plain",
          "application/json",
          "text/json"
        ],
        "StatusCode": 401
      }
    ]
  },
  {
    "ContainingType": "BlazorCARS.HealthShield.WebAPI.Controllers.HospitalController",
    "Method": "CreateAsync",
    "RelativePath": "api/hospitals",
    "HttpMethod": "POST",
    "IsController": true,
    "Order": 0,
    "Parameters": [
      {
        "Name": "requestDTO",
        "Type": "BlazorCARS.HealthShield.DataObject.DTO.HospitalCreateDTO",
        "IsRequired": true
      }
    ],
    "ReturnTypes": [
      {
        "Type": "BlazorCARS.HealthShield.Utility.Response.APIResponse",
        "MediaTypes": [
          "text/plain",
          "application/json",
          "text/json"
        ],
        "StatusCode": 201
      },
      {
        "Type": "Microsoft.AspNetCore.Mvc.ProblemDetails",
        "MediaTypes": [
          "text/plain",
          "application/json",
          "text/json"
        ],
        "StatusCode": 400
      },
      {
        "Type": "System.Void",
        "MediaTypes": [],
        "StatusCode": 500
      }
    ]
  },
  {
    "ContainingType": "BlazorCARS.HealthShield.WebAPI.Controllers.HospitalController",
    "Method": "GetByIdAsync",
    "RelativePath": "api/hospitals/{id}",
    "HttpMethod": "GET",
    "IsController": true,
    "Order": 0,
    "Parameters": [
      {
        "Name": "id",
        "Type": "System.Int32",
        "IsRequired": true
      }
    ],
    "ReturnTypes": [
      {
        "Type": "Microsoft.AspNetCore.Mvc.ProblemDetails",
        "MediaTypes": [
          "text/plain",
          "application/json",
          "text/json"
        ],
        "StatusCode": 400
      },
      {
        "Type": "Microsoft.AspNetCore.Mvc.ProblemDetails",
        "MediaTypes": [
          "text/plain",
          "application/json",
          "text/json"
        ],
        "StatusCode": 404
      },
      {
        "Type": "BlazorCARS.HealthShield.Utility.Response.APIResponse",
        "MediaTypes": [
          "text/plain",
          "application/json",
          "text/json"
        ],
        "StatusCode": 200
      },
      {
        "Type": "System.Void",
        "MediaTypes": [],
        "StatusCode": 500
      }
    ]
  },
  {
    "ContainingType": "BlazorCARS.HealthShield.WebAPI.Controllers.HospitalController",
    "Method": "UpdateAsync",
    "RelativePath": "api/hospitals/{id}",
    "HttpMethod": "PUT",
    "IsController": true,
    "Order": 0,
    "Parameters": [
      {
        "Name": "id",
        "Type": "System.Int32",
        "IsRequired": true
      },
      {
        "Name": "requestDTO",
        "Type": "BlazorCARS.HealthShield.DataObject.DTO.HospitalUpdateDTO",
        "IsRequired": true
      }
    ],
    "ReturnTypes": [
      {
        "Type": "BlazorCARS.HealthShield.Utility.Response.APIResponse",
        "MediaTypes": [
          "text/plain",
          "application/json",
          "text/json"
        ],
        "StatusCode": 200
      },
      {
        "Type": "Microsoft.AspNetCore.Mvc.ProblemDetails",
        "MediaTypes": [
          "text/plain",
          "application/json",
          "text/json"
        ],
        "StatusCode": 404
      },
      {
        "Type": "System.Void",
        "MediaTypes": [],
        "StatusCode": 500
      },
      {
        "Type": "Microsoft.AspNetCore.Mvc.ProblemDetails",
        "MediaTypes": [
          "text/plain",
          "application/json",
          "text/json"
        ],
        "StatusCode": 400
      }
    ]
  },
  {
    "ContainingType": "BlazorCARS.HealthShield.WebAPI.Controllers.HospitalController",
    "Method": "DeleteAync",
    "RelativePath": "api/hospitals/{id}/{DeletedHospital}",
    "HttpMethod": "DELETE",
    "IsController": true,
    "Order": 0,
    "Parameters": [
      {
        "Name": "id",
        "Type": "System.Int32",
        "IsRequired": true
      },
      {
        "Name": "DeletedHospital",
        "Type": "System.String",
        "IsRequired": true
      }
    ],
    "ReturnTypes": [
      {
        "Type": "System.Void",
        "MediaTypes": [],
        "StatusCode": 500
      },
      {
        "Type": "Microsoft.AspNetCore.Mvc.ProblemDetails",
        "MediaTypes": [
          "text/plain",
          "application/json",
          "text/json"
        ],
        "StatusCode": 400
      },
      {
        "Type": "System.Void",
        "MediaTypes": [],
        "StatusCode": 204
      },
      {
        "Type": "Microsoft.AspNetCore.Mvc.ProblemDetails",
        "MediaTypes": [
          "text/plain",
          "application/json",
          "text/json"
        ],
        "StatusCode": 404
      }
    ]
  },
  {
    "ContainingType": "BlazorCARS.HealthShield.WebAPI.Controllers.InventoryController",
    "Method": "GetAllSync",
    "RelativePath": "api/inventory",
    "HttpMethod": "GET",
    "IsController": true,
    "Order": 0,
    "Parameters": [
      {
        "Name": "pageSize",
        "Type": "System.Int32",
        "IsRequired": false
      },
      {
        "Name": "pageNumber",
        "Type": "System.Int32",
        "IsRequired": false
      }
    ],
    "ReturnTypes": [
      {
        "Type": "BlazorCARS.HealthShield.Utility.Response.APIResponse",
        "MediaTypes": [
          "text/plain",
          "application/json",
          "text/json"
        ],
        "StatusCode": 200
      }
    ]
  },
  {
    "ContainingType": "BlazorCARS.HealthShield.WebAPI.Controllers.InventoryController",
    "Method": "CreateAsync",
    "RelativePath": "api/inventory",
    "HttpMethod": "POST",
    "IsController": true,
    "Order": 0,
    "Parameters": [
      {
        "Name": "requestDTO",
        "Type": "BlazorCARS.HealthShield.DataObject.DTO.InventoryCreateDTO",
        "IsRequired": true
      }
    ],
    "ReturnTypes": [
      {
        "Type": "BlazorCARS.HealthShield.Utility.Response.APIResponse",
        "MediaTypes": [
          "text/plain",
          "application/json",
          "text/json"
        ],
        "StatusCode": 201
      },
      {
        "Type": "Microsoft.AspNetCore.Mvc.ProblemDetails",
        "MediaTypes": [
          "text/plain",
          "application/json",
          "text/json"
        ],
        "StatusCode": 400
      },
      {
        "Type": "System.Void",
        "MediaTypes": [],
        "StatusCode": 500
      }
    ]
  },
  {
    "ContainingType": "BlazorCARS.HealthShield.WebAPI.Controllers.InventoryController",
    "Method": "GetByIdAsync",
    "RelativePath": "api/inventory/{id}",
    "HttpMethod": "GET",
    "IsController": true,
    "Order": 0,
    "Parameters": [
      {
        "Name": "id",
        "Type": "System.Int32",
        "IsRequired": true
      }
    ],
    "ReturnTypes": [
      {
        "Type": "Microsoft.AspNetCore.Mvc.ProblemDetails",
        "MediaTypes": [
          "text/plain",
          "application/json",
          "text/json"
        ],
        "StatusCode": 400
      },
      {
        "Type": "Microsoft.AspNetCore.Mvc.ProblemDetails",
        "MediaTypes": [
          "text/plain",
          "application/json",
          "text/json"
        ],
        "StatusCode": 404
      },
      {
        "Type": "BlazorCARS.HealthShield.Utility.Response.APIResponse",
        "MediaTypes": [
          "text/plain",
          "application/json",
          "text/json"
        ],
        "StatusCode": 200
      },
      {
        "Type": "System.Void",
        "MediaTypes": [],
        "StatusCode": 500
      }
    ]
  },
  {
    "ContainingType": "BlazorCARS.HealthShield.WebAPI.Controllers.InventoryController",
    "Method": "UpdateAsync",
    "RelativePath": "api/inventory/{id}",
    "HttpMethod": "PUT",
    "IsController": true,
    "Order": 0,
    "Parameters": [
      {
        "Name": "id",
        "Type": "System.Int32",
        "IsRequired": true
      },
      {
        "Name": "requestDTO",
        "Type": "BlazorCARS.HealthShield.DataObject.DTO.InventoryUpdateDTO",
        "IsRequired": true
      }
    ],
    "ReturnTypes": [
      {
        "Type": "BlazorCARS.HealthShield.Utility.Response.APIResponse",
        "MediaTypes": [
          "text/plain",
          "application/json",
          "text/json"
        ],
        "StatusCode": 200
      },
      {
        "Type": "Microsoft.AspNetCore.Mvc.ProblemDetails",
        "MediaTypes": [
          "text/plain",
          "application/json",
          "text/json"
        ],
        "StatusCode": 404
      },
      {
        "Type": "System.Void",
        "MediaTypes": [],
        "StatusCode": 500
      },
      {
        "Type": "Microsoft.AspNetCore.Mvc.ProblemDetails",
        "MediaTypes": [
          "text/plain",
          "application/json",
          "text/json"
        ],
        "StatusCode": 400
      }
    ]
  },
  {
    "ContainingType": "BlazorCARS.HealthShield.WebAPI.Controllers.InventoryController",
    "Method": "DeleteAync",
    "RelativePath": "api/inventory/{id}",
    "HttpMethod": "DELETE",
    "IsController": true,
    "Order": 0,
    "Parameters": [
      {
        "Name": "id",
        "Type": "System.Int32",
        "IsRequired": true
      }
    ],
    "ReturnTypes": [
      {
        "Type": "System.Void",
        "MediaTypes": [],
        "StatusCode": 500
      },
      {
        "Type": "Microsoft.AspNetCore.Mvc.ProblemDetails",
        "MediaTypes": [
          "text/plain",
          "application/json",
          "text/json"
        ],
        "StatusCode": 400
      },
      {
        "Type": "System.Void",
        "MediaTypes": [],
        "StatusCode": 204
      },
      {
        "Type": "Microsoft.AspNetCore.Mvc.ProblemDetails",
        "MediaTypes": [
          "text/plain",
          "application/json",
          "text/json"
        ],
        "StatusCode": 404
      }
    ]
  },
  {
    "ContainingType": "BlazorCARS.HealthShield.WebAPI.Controllers.InventoryTransactionController",
    "Method": "GetAllSync",
    "RelativePath": "api/inventorytransactions",
    "HttpMethod": "GET",
    "IsController": true,
    "Order": 0,
    "Parameters": [
      {
        "Name": "pageSize",
        "Type": "System.Int32",
        "IsRequired": false
      },
      {
        "Name": "pageNumber",
        "Type": "System.Int32",
        "IsRequired": false
      }
    ],
    "ReturnTypes": [
      {
        "Type": "BlazorCARS.HealthShield.Utility.Response.APIResponse",
        "MediaTypes": [
          "text/plain",
          "application/json",
          "text/json"
        ],
        "StatusCode": 200
      }
    ]
  },
  {
    "ContainingType": "BlazorCARS.HealthShield.WebAPI.Controllers.InventoryTransactionController",
    "Method": "CreateAsync",
    "RelativePath": "api/inventorytransactions",
    "HttpMethod": "POST",
    "IsController": true,
    "Order": 0,
    "Parameters": [
      {
        "Name": "requestDTO",
        "Type": "BlazorCARS.HealthShield.DataObject.DTO.InventoryTransactionCreateDTO",
        "IsRequired": true
      }
    ],
    "ReturnTypes": [
      {
        "Type": "BlazorCARS.HealthShield.Utility.Response.APIResponse",
        "MediaTypes": [
          "text/plain",
          "application/json",
          "text/json"
        ],
        "StatusCode": 201
      },
      {
        "Type": "Microsoft.AspNetCore.Mvc.ProblemDetails",
        "MediaTypes": [
          "text/plain",
          "application/json",
          "text/json"
        ],
        "StatusCode": 400
      },
      {
        "Type": "System.Void",
        "MediaTypes": [],
        "StatusCode": 500
      }
    ]
  },
  {
    "ContainingType": "BlazorCARS.HealthShield.WebAPI.Controllers.InventoryTransactionController",
    "Method": "GetByIdAsync",
    "RelativePath": "api/inventorytransactions/{id}",
    "HttpMethod": "GET",
    "IsController": true,
    "Order": 0,
    "Parameters": [
      {
        "Name": "id",
        "Type": "System.Int32",
        "IsRequired": true
      }
    ],
    "ReturnTypes": [
      {
        "Type": "Microsoft.AspNetCore.Mvc.ProblemDetails",
        "MediaTypes": [
          "text/plain",
          "application/json",
          "text/json"
        ],
        "StatusCode": 400
      },
      {
        "Type": "Microsoft.AspNetCore.Mvc.ProblemDetails",
        "MediaTypes": [
          "text/plain",
          "application/json",
          "text/json"
        ],
        "StatusCode": 404
      },
      {
        "Type": "BlazorCARS.HealthShield.Utility.Response.APIResponse",
        "MediaTypes": [
          "text/plain",
          "application/json",
          "text/json"
        ],
        "StatusCode": 200
      },
      {
        "Type": "System.Void",
        "MediaTypes": [],
        "StatusCode": 500
      }
    ]
  },
  {
    "ContainingType": "BlazorCARS.HealthShield.WebAPI.Controllers.InventoryTransactionController",
    "Method": "UpdateAsync",
    "RelativePath": "api/inventorytransactions/{id}",
    "HttpMethod": "PUT",
    "IsController": true,
    "Order": 0,
    "Parameters": [
      {
        "Name": "id",
        "Type": "System.Int32",
        "IsRequired": true
      },
      {
        "Name": "requestDTO",
        "Type": "BlazorCARS.HealthShield.DataObject.DTO.InventoryTransactionUpdateDTO",
        "IsRequired": true
      }
    ],
    "ReturnTypes": [
      {
        "Type": "BlazorCARS.HealthShield.Utility.Response.APIResponse",
        "MediaTypes": [
          "text/plain",
          "application/json",
          "text/json"
        ],
        "StatusCode": 200
      },
      {
        "Type": "Microsoft.AspNetCore.Mvc.ProblemDetails",
        "MediaTypes": [
          "text/plain",
          "application/json",
          "text/json"
        ],
        "StatusCode": 404
      },
      {
        "Type": "System.Void",
        "MediaTypes": [],
        "StatusCode": 500
      },
      {
        "Type": "Microsoft.AspNetCore.Mvc.ProblemDetails",
        "MediaTypes": [
          "text/plain",
          "application/json",
          "text/json"
        ],
        "StatusCode": 400
      }
    ]
  },
  {
    "ContainingType": "BlazorCARS.HealthShield.WebAPI.Controllers.InventoryTransactionController",
    "Method": "DeleteAync",
    "RelativePath": "api/inventorytransactions/{id}",
    "HttpMethod": "DELETE",
    "IsController": true,
    "Order": 0,
    "Parameters": [
      {
        "Name": "id",
        "Type": "System.Int32",
        "IsRequired": true
      }
    ],
    "ReturnTypes": [
      {
        "Type": "System.Void",
        "MediaTypes": [],
        "StatusCode": 500
      },
      {
        "Type": "Microsoft.AspNetCore.Mvc.ProblemDetails",
        "MediaTypes": [
          "text/plain",
          "application/json",
          "text/json"
        ],
        "StatusCode": 400
      },
      {
        "Type": "System.Void",
        "MediaTypes": [],
        "StatusCode": 204
      },
      {
        "Type": "Microsoft.AspNetCore.Mvc.ProblemDetails",
        "MediaTypes": [
          "text/plain",
          "application/json",
          "text/json"
        ],
        "StatusCode": 404
      }
    ]
  },
  {
    "ContainingType": "BlazorCARS.HealthShield.WebAPI.Controllers.RecipientRegistryController",
    "Method": "CreateAsync",
    "RelativePath": "api/recipientregistry",
    "HttpMethod": "POST",
    "IsController": true,
    "Order": 0,
    "Parameters": [
      {
        "Name": "requestDTO",
        "Type": "BlazorCARS.HealthShield.DataObject.DTO.RecipientRegistryDTO",
        "IsRequired": true
      }
    ],
    "ReturnTypes": [
      {
        "Type": "BlazorCARS.HealthShield.Utility.Response.APIResponse",
        "MediaTypes": [
          "text/plain",
          "application/json",
          "text/json"
        ],
        "StatusCode": 201
      },
      {
        "Type": "Microsoft.AspNetCore.Mvc.ProblemDetails",
        "MediaTypes": [
          "text/plain",
          "application/json",
          "text/json"
        ],
        "StatusCode": 400
      },
      {
        "Type": "System.Void",
        "MediaTypes": [],
        "StatusCode": 500
      }
    ]
  },
  {
    "ContainingType": "BlazorCARS.HealthShield.WebAPI.Controllers.RecipientController",
    "Method": "GetAllAsync",
    "RelativePath": "api/recipients",
    "HttpMethod": "GET",
    "IsController": true,
    "Order": 0,
    "Parameters": [
      {
        "Name": "pageSize",
        "Type": "System.Int32",
        "IsRequired": false
      },
      {
        "Name": "pageNumber",
        "Type": "System.Int32",
        "IsRequired": false
      }
    ],
    "ReturnTypes": [
      {
        "Type": "BlazorCARS.HealthShield.Utility.Response.APIResponse",
        "MediaTypes": [
          "text/plain",
          "application/json",
          "text/json"
        ],
        "StatusCode": 200
      },
      {
        "Type": "Microsoft.AspNetCore.Mvc.ProblemDetails",
        "MediaTypes": [
          "text/plain",
          "application/json",
          "text/json"
        ],
        "StatusCode": 400
      },
      {
        "Type": "System.Void",
        "MediaTypes": [],
        "StatusCode": 500
      },
      {
        "Type": "Microsoft.AspNetCore.Mvc.ProblemDetails",
        "MediaTypes": [
          "text/plain",
          "application/json",
          "text/json"
        ],
        "StatusCode": 401
      }
    ]
  },
  {
    "ContainingType": "BlazorCARS.HealthShield.WebAPI.Controllers.RecipientController",
    "Method": "CreateAsync",
    "RelativePath": "api/recipients",
    "HttpMethod": "POST",
    "IsController": true,
    "Order": 0,
    "Parameters": [
      {
        "Name": "requestDTO",
        "Type": "BlazorCARS.HealthShield.DataObject.DTO.RecipientCreateDTO",
        "IsRequired": true
      }
    ],
    "ReturnTypes": [
      {
        "Type": "BlazorCARS.HealthShield.Utility.Response.APIResponse",
        "MediaTypes": [
          "text/plain",
          "application/json",
          "text/json"
        ],
        "StatusCode": 201
      },
      {
        "Type": "Microsoft.AspNetCore.Mvc.ProblemDetails",
        "MediaTypes": [
          "text/plain",
          "application/json",
          "text/json"
        ],
        "StatusCode": 400
      },
      {
        "Type": "System.Void",
        "MediaTypes": [],
        "StatusCode": 500
      }
    ]
  },
  {
    "ContainingType": "BlazorCARS.HealthShield.WebAPI.Controllers.RecipientController",
    "Method": "GetByIdAsync",
    "RelativePath": "api/recipients/{id}",
    "HttpMethod": "GET",
    "IsController": true,
    "Order": 0,
    "Parameters": [
      {
        "Name": "id",
        "Type": "System.Int32",
        "IsRequired": true
      }
    ],
    "ReturnTypes": [
      {
        "Type": "Microsoft.AspNetCore.Mvc.ProblemDetails",
        "MediaTypes": [
          "text/plain",
          "application/json",
          "text/json"
        ],
        "StatusCode": 400
      },
      {
        "Type": "Microsoft.AspNetCore.Mvc.ProblemDetails",
        "MediaTypes": [
          "text/plain",
          "application/json",
          "text/json"
        ],
        "StatusCode": 404
      },
      {
        "Type": "BlazorCARS.HealthShield.Utility.Response.APIResponse",
        "MediaTypes": [
          "text/plain",
          "application/json",
          "text/json"
        ],
        "StatusCode": 200
      },
      {
        "Type": "System.Void",
        "MediaTypes": [],
        "StatusCode": 500
      }
    ]
  },
  {
    "ContainingType": "BlazorCARS.HealthShield.WebAPI.Controllers.RecipientController",
    "Method": "UpdateAsync",
    "RelativePath": "api/recipients/{id}",
    "HttpMethod": "PUT",
    "IsController": true,
    "Order": 0,
    "Parameters": [
      {
        "Name": "id",
        "Type": "System.Int32",
        "IsRequired": true
      },
      {
        "Name": "requestDTO",
        "Type": "BlazorCARS.HealthShield.DataObject.DTO.RecipientUpdateDTO",
        "IsRequired": true
      }
    ],
    "ReturnTypes": [
      {
        "Type": "BlazorCARS.HealthShield.Utility.Response.APIResponse",
        "MediaTypes": [
          "text/plain",
          "application/json",
          "text/json"
        ],
        "StatusCode": 200
      },
      {
        "Type": "Microsoft.AspNetCore.Mvc.ProblemDetails",
        "MediaTypes": [
          "text/plain",
          "application/json",
          "text/json"
        ],
        "StatusCode": 404
      },
      {
        "Type": "System.Void",
        "MediaTypes": [],
        "StatusCode": 500
      },
      {
        "Type": "Microsoft.AspNetCore.Mvc.ProblemDetails",
        "MediaTypes": [
          "text/plain",
          "application/json",
          "text/json"
        ],
        "StatusCode": 400
      }
    ]
  },
  {
    "ContainingType": "BlazorCARS.HealthShield.WebAPI.Controllers.RecipientController",
    "Method": "DeleteAync",
    "RelativePath": "api/recipients/{id}/{DeletedRecipient}",
    "HttpMethod": "DELETE",
    "IsController": true,
    "Order": 0,
    "Parameters": [
      {
        "Name": "id",
        "Type": "System.Int32",
        "IsRequired": true
      },
      {
        "Name": "DeletedUser",
        "Type": "System.String",
        "IsRequired": false
      },
      {
        "Name": "DeletedRecipient",
        "Type": "",
        "IsRequired": true
      }
    ],
    "ReturnTypes": [
      {
        "Type": "System.Void",
        "MediaTypes": [],
        "StatusCode": 500
      },
      {
        "Type": "Microsoft.AspNetCore.Mvc.ProblemDetails",
        "MediaTypes": [
          "text/plain",
          "application/json",
          "text/json"
        ],
        "StatusCode": 400
      },
      {
        "Type": "System.Void",
        "MediaTypes": [],
        "StatusCode": 204
      },
      {
        "Type": "Microsoft.AspNetCore.Mvc.ProblemDetails",
        "MediaTypes": [
          "text/plain",
          "application/json",
          "text/json"
        ],
        "StatusCode": 404
      }
    ]
  },
  {
    "ContainingType": "BlazorCARS.HealthShield.WebAPI.Controllers.RecipientController",
    "Method": "GetAllDependantsAsync",
    "RelativePath": "api/recipients/Depandant/{id}",
    "HttpMethod": "GET",
    "IsController": true,
    "Order": 0,
    "Parameters": [
      {
        "Name": "id",
        "Type": "System.Int32",
        "IsRequired": true
      }
    ],
    "ReturnTypes": [
      {
        "Type": "BlazorCARS.HealthShield.Utility.Response.APIResponse",
        "MediaTypes": [
          "text/plain",
          "application/json",
          "text/json"
        ],
        "StatusCode": 200
      },
      {
        "Type": "Microsoft.AspNetCore.Mvc.ProblemDetails",
        "MediaTypes": [
          "text/plain",
          "application/json",
          "text/json"
        ],
        "StatusCode": 400
      },
      {
        "Type": "System.Void",
        "MediaTypes": [],
        "StatusCode": 500
      },
      {
        "Type": "Microsoft.AspNetCore.Mvc.ProblemDetails",
        "MediaTypes": [
          "text/plain",
          "application/json",
          "text/json"
        ],
        "StatusCode": 401
      }
    ]
  },
  {
    "ContainingType": "BlazorCARS.HealthShield.WebAPI.Controllers.StateController",
    "Method": "GetAllAsync",
    "RelativePath": "api/states",
    "HttpMethod": "GET",
    "IsController": true,
    "Order": 0,
    "Parameters": [
      {
        "Name": "pageSize",
        "Type": "System.Int32",
        "IsRequired": false
      },
      {
        "Name": "pageNumber",
        "Type": "System.Int32",
        "IsRequired": false
      }
    ],
    "ReturnTypes": [
      {
        "Type": "BlazorCARS.HealthShield.Utility.Response.APIResponse",
        "MediaTypes": [
          "text/plain",
          "application/json",
          "text/json"
        ],
        "StatusCode": 200
      },
      {
        "Type": "Microsoft.AspNetCore.Mvc.ProblemDetails",
        "MediaTypes": [
          "text/plain",
          "application/json",
          "text/json"
        ],
        "StatusCode": 400
      },
      {
        "Type": "System.Void",
        "MediaTypes": [],
        "StatusCode": 500
      },
      {
        "Type": "Microsoft.AspNetCore.Mvc.ProblemDetails",
        "MediaTypes": [
          "text/plain",
          "application/json",
          "text/json"
        ],
        "StatusCode": 401
      }
    ]
  },
  {
    "ContainingType": "BlazorCARS.HealthShield.WebAPI.Controllers.StateController",
    "Method": "CreateAsync",
    "RelativePath": "api/states",
    "HttpMethod": "POST",
    "IsController": true,
    "Order": 0,
    "Parameters": [
      {
        "Name": "requestDTO",
        "Type": "BlazorCARS.HealthShield.DataObject.DTO.StateCreateDTO",
        "IsRequired": true
      }
    ],
    "ReturnTypes": [
      {
        "Type": "BlazorCARS.HealthShield.Utility.Response.APIResponse",
        "MediaTypes": [
          "text/plain",
          "application/json",
          "text/json"
        ],
        "StatusCode": 201
      },
      {
        "Type": "Microsoft.AspNetCore.Mvc.ProblemDetails",
        "MediaTypes": [
          "text/plain",
          "application/json",
          "text/json"
        ],
        "StatusCode": 400
      },
      {
        "Type": "System.Void",
        "MediaTypes": [],
        "StatusCode": 500
      }
    ]
  },
  {
    "ContainingType": "BlazorCARS.HealthShield.WebAPI.Controllers.StateController",
    "Method": "GetByIdAsync",
    "RelativePath": "api/states/{id}",
    "HttpMethod": "GET",
    "IsController": true,
    "Order": 0,
    "Parameters": [
      {
        "Name": "id",
        "Type": "System.Int32",
        "IsRequired": true
      }
    ],
    "ReturnTypes": [
      {
        "Type": "Microsoft.AspNetCore.Mvc.ProblemDetails",
        "MediaTypes": [
          "text/plain",
          "application/json",
          "text/json"
        ],
        "StatusCode": 400
      },
      {
        "Type": "Microsoft.AspNetCore.Mvc.ProblemDetails",
        "MediaTypes": [
          "text/plain",
          "application/json",
          "text/json"
        ],
        "StatusCode": 404
      },
      {
        "Type": "BlazorCARS.HealthShield.Utility.Response.APIResponse",
        "MediaTypes": [
          "text/plain",
          "application/json",
          "text/json"
        ],
        "StatusCode": 200
      },
      {
        "Type": "System.Void",
        "MediaTypes": [],
        "StatusCode": 500
      }
    ]
  },
  {
    "ContainingType": "BlazorCARS.HealthShield.WebAPI.Controllers.StateController",
    "Method": "UpdateAsync",
    "RelativePath": "api/states/{id}",
    "HttpMethod": "PUT",
    "IsController": true,
    "Order": 0,
    "Parameters": [
      {
        "Name": "id",
        "Type": "System.Int32",
        "IsRequired": true
      },
      {
        "Name": "requestDTO",
        "Type": "BlazorCARS.HealthShield.DataObject.DTO.StateUpdateDTO",
        "IsRequired": true
      }
    ],
    "ReturnTypes": [
      {
        "Type": "BlazorCARS.HealthShield.Utility.Response.APIResponse",
        "MediaTypes": [
          "text/plain",
          "application/json",
          "text/json"
        ],
        "StatusCode": 200
      },
      {
        "Type": "Microsoft.AspNetCore.Mvc.ProblemDetails",
        "MediaTypes": [
          "text/plain",
          "application/json",
          "text/json"
        ],
        "StatusCode": 404
      },
      {
        "Type": "System.Void",
        "MediaTypes": [],
        "StatusCode": 500
      },
      {
        "Type": "Microsoft.AspNetCore.Mvc.ProblemDetails",
        "MediaTypes": [
          "text/plain",
          "application/json",
          "text/json"
        ],
        "StatusCode": 400
      }
    ]
  },
  {
    "ContainingType": "BlazorCARS.HealthShield.WebAPI.Controllers.StateController",
    "Method": "DeleteAync",
    "RelativePath": "api/states/{id}/{DeletedUser}",
    "HttpMethod": "DELETE",
    "IsController": true,
    "Order": 0,
    "Parameters": [
      {
        "Name": "id",
        "Type": "System.Int32",
        "IsRequired": true
      },
      {
        "Name": "DeletedUser",
        "Type": "System.String",
        "IsRequired": true
      }
    ],
    "ReturnTypes": [
      {
        "Type": "System.Void",
        "MediaTypes": [],
        "StatusCode": 500
      },
      {
        "Type": "Microsoft.AspNetCore.Mvc.ProblemDetails",
        "MediaTypes": [
          "text/plain",
          "application/json",
          "text/json"
        ],
        "StatusCode": 400
      },
      {
        "Type": "System.Void",
        "MediaTypes": [],
        "StatusCode": 204
      },
      {
        "Type": "Microsoft.AspNetCore.Mvc.ProblemDetails",
        "MediaTypes": [
          "text/plain",
          "application/json",
          "text/json"
        ],
        "StatusCode": 404
      }
    ]
  },
  {
    "ContainingType": "BlazorCARS.HealthShield.WebAPI.Controllers.UserRoleController",
    "Method": "GetAllAsync",
    "RelativePath": "api/userroles",
    "HttpMethod": "GET",
    "IsController": true,
    "Order": 0,
    "Parameters": [
      {
        "Name": "pageSize",
        "Type": "System.Int32",
        "IsRequired": false
      },
      {
        "Name": "pageNumber",
        "Type": "System.Int32",
        "IsRequired": false
      }
    ],
    "ReturnTypes": [
      {
        "Type": "BlazorCARS.HealthShield.Utility.Response.APIResponse",
        "MediaTypes": [
          "text/plain",
          "application/json",
          "text/json"
        ],
        "StatusCode": 200
      },
      {
        "Type": "Microsoft.AspNetCore.Mvc.ProblemDetails",
        "MediaTypes": [
          "text/plain",
          "application/json",
          "text/json"
        ],
        "StatusCode": 400
      },
      {
        "Type": "System.Void",
        "MediaTypes": [],
        "StatusCode": 500
      },
      {
        "Type": "Microsoft.AspNetCore.Mvc.ProblemDetails",
        "MediaTypes": [
          "text/plain",
          "application/json",
          "text/json"
        ],
        "StatusCode": 401
      }
    ]
  },
  {
    "ContainingType": "BlazorCARS.HealthShield.WebAPI.Controllers.UserRoleController",
    "Method": "CreateAsync",
    "RelativePath": "api/userroles",
    "HttpMethod": "POST",
    "IsController": true,
    "Order": 0,
    "Parameters": [
      {
        "Name": "requestDTO",
        "Type": "BlazorCARS.HealthShield.DataObject.DTO.UserRoleCreateDTO",
        "IsRequired": true
      }
    ],
    "ReturnTypes": [
      {
        "Type": "BlazorCARS.HealthShield.Utility.Response.APIResponse",
        "MediaTypes": [
          "text/plain",
          "application/json",
          "text/json"
        ],
        "StatusCode": 201
      },
      {
        "Type": "Microsoft.AspNetCore.Mvc.ProblemDetails",
        "MediaTypes": [
          "text/plain",
          "application/json",
          "text/json"
        ],
        "StatusCode": 400
      },
      {
        "Type": "System.Void",
        "MediaTypes": [],
        "StatusCode": 500
      }
    ]
  },
  {
    "ContainingType": "BlazorCARS.HealthShield.WebAPI.Controllers.UserRoleController",
    "Method": "GetByIdAsync",
    "RelativePath": "api/userroles/{id}",
    "HttpMethod": "GET",
    "IsController": true,
    "Order": 0,
    "Parameters": [
      {
        "Name": "id",
        "Type": "System.Int32",
        "IsRequired": true
      }
    ],
    "ReturnTypes": [
      {
        "Type": "Microsoft.AspNetCore.Mvc.ProblemDetails",
        "MediaTypes": [
          "text/plain",
          "application/json",
          "text/json"
        ],
        "StatusCode": 400
      },
      {
        "Type": "Microsoft.AspNetCore.Mvc.ProblemDetails",
        "MediaTypes": [
          "text/plain",
          "application/json",
          "text/json"
        ],
        "StatusCode": 404
      },
      {
        "Type": "BlazorCARS.HealthShield.Utility.Response.APIResponse",
        "MediaTypes": [
          "text/plain",
          "application/json",
          "text/json"
        ],
        "StatusCode": 200
      },
      {
        "Type": "System.Void",
        "MediaTypes": [],
        "StatusCode": 500
      }
    ]
  },
  {
    "ContainingType": "BlazorCARS.HealthShield.WebAPI.Controllers.UserRoleController",
    "Method": "UpdateAsync",
    "RelativePath": "api/userroles/{id}",
    "HttpMethod": "PUT",
    "IsController": true,
    "Order": 0,
    "Parameters": [
      {
        "Name": "id",
        "Type": "System.Int32",
        "IsRequired": true
      },
      {
        "Name": "requestDTO",
        "Type": "BlazorCARS.HealthShield.DataObject.DTO.UserRoleUpdateDTO",
        "IsRequired": true
      }
    ],
    "ReturnTypes": [
      {
        "Type": "BlazorCARS.HealthShield.Utility.Response.APIResponse",
        "MediaTypes": [
          "text/plain",
          "application/json",
          "text/json"
        ],
        "StatusCode": 200
      },
      {
        "Type": "Microsoft.AspNetCore.Mvc.ProblemDetails",
        "MediaTypes": [
          "text/plain",
          "application/json",
          "text/json"
        ],
        "StatusCode": 404
      },
      {
        "Type": "System.Void",
        "MediaTypes": [],
        "StatusCode": 500
      },
      {
        "Type": "Microsoft.AspNetCore.Mvc.ProblemDetails",
        "MediaTypes": [
          "text/plain",
          "application/json",
          "text/json"
        ],
        "StatusCode": 400
      }
    ]
  },
  {
    "ContainingType": "BlazorCARS.HealthShield.WebAPI.Controllers.UserRoleController",
    "Method": "DeleteAync",
    "RelativePath": "api/userroles/{id}/{DeletedUser}",
    "HttpMethod": "DELETE",
    "IsController": true,
    "Order": 0,
    "Parameters": [
      {
        "Name": "id",
        "Type": "System.Int32",
        "IsRequired": true
      },
      {
        "Name": "DeletedUser",
        "Type": "System.String",
        "IsRequired": true
      }
    ],
    "ReturnTypes": [
      {
        "Type": "System.Void",
        "MediaTypes": [],
        "StatusCode": 500
      },
      {
        "Type": "Microsoft.AspNetCore.Mvc.ProblemDetails",
        "MediaTypes": [
          "text/plain",
          "application/json",
          "text/json"
        ],
        "StatusCode": 400
      },
      {
        "Type": "System.Void",
        "MediaTypes": [],
        "StatusCode": 204
      },
      {
        "Type": "Microsoft.AspNetCore.Mvc.ProblemDetails",
        "MediaTypes": [
          "text/plain",
          "application/json",
          "text/json"
        ],
        "StatusCode": 404
      }
    ]
  },
  {
    "ContainingType": "BlazorCARS.HealthShield.WebAPI.Controllers.UserStoreController",
    "Method": "GetAllAsync",
    "RelativePath": "api/userstories",
    "HttpMethod": "GET",
    "IsController": true,
    "Order": 0,
    "Parameters": [
      {
        "Name": "pageSize",
        "Type": "System.Int32",
        "IsRequired": false
      },
      {
        "Name": "pageNumber",
        "Type": "System.Int32",
        "IsRequired": false
      }
    ],
    "ReturnTypes": [
      {
        "Type": "BlazorCARS.HealthShield.Utility.Response.APIResponse",
        "MediaTypes": [
          "text/plain",
          "application/json",
          "text/json"
        ],
        "StatusCode": 200
      },
      {
        "Type": "Microsoft.AspNetCore.Mvc.ProblemDetails",
        "MediaTypes": [
          "text/plain",
          "application/json",
          "text/json"
        ],
        "StatusCode": 400
      },
      {
        "Type": "System.Void",
        "MediaTypes": [],
        "StatusCode": 500
      },
      {
        "Type": "Microsoft.AspNetCore.Mvc.ProblemDetails",
        "MediaTypes": [
          "text/plain",
          "application/json",
          "text/json"
        ],
        "StatusCode": 401
      }
    ]
  },
  {
    "ContainingType": "BlazorCARS.HealthShield.WebAPI.Controllers.UserStoreController",
    "Method": "CreateAsync",
    "RelativePath": "api/userstories",
    "HttpMethod": "POST",
    "IsController": true,
    "Order": 0,
    "Parameters": [
      {
        "Name": "requestDTO",
        "Type": "BlazorCARS.HealthShield.DataObject.DTO.UserStoreCreateDTO",
        "IsRequired": true
      }
    ],
    "ReturnTypes": [
      {
        "Type": "BlazorCARS.HealthShield.Utility.Response.APIResponse",
        "MediaTypes": [
          "text/plain",
          "application/json",
          "text/json"
        ],
        "StatusCode": 201
      },
      {
        "Type": "Microsoft.AspNetCore.Mvc.ProblemDetails",
        "MediaTypes": [
          "text/plain",
          "application/json",
          "text/json"
        ],
        "StatusCode": 400
      },
      {
        "Type": "System.Void",
        "MediaTypes": [],
        "StatusCode": 500
      }
    ]
  },
  {
    "ContainingType": "BlazorCARS.HealthShield.WebAPI.Controllers.UserStoreController",
    "Method": "GetByIdAsync",
    "RelativePath": "api/userstories/{id}",
    "HttpMethod": "GET",
    "IsController": true,
    "Order": 0,
    "Parameters": [
      {
        "Name": "id",
        "Type": "System.Int32",
        "IsRequired": true
      }
    ],
    "ReturnTypes": [
      {
        "Type": "Microsoft.AspNetCore.Mvc.ProblemDetails",
        "MediaTypes": [
          "text/plain",
          "application/json",
          "text/json"
        ],
        "StatusCode": 400
      },
      {
        "Type": "Microsoft.AspNetCore.Mvc.ProblemDetails",
        "MediaTypes": [
          "text/plain",
          "application/json",
          "text/json"
        ],
        "StatusCode": 404
      },
      {
        "Type": "BlazorCARS.HealthShield.Utility.Response.APIResponse",
        "MediaTypes": [
          "text/plain",
          "application/json",
          "text/json"
        ],
        "StatusCode": 200
      },
      {
        "Type": "System.Void",
        "MediaTypes": [],
        "StatusCode": 500
      }
    ]
  },
  {
    "ContainingType": "BlazorCARS.HealthShield.WebAPI.Controllers.UserStoreController",
    "Method": "UpdateAsync",
    "RelativePath": "api/userstories/{id}",
    "HttpMethod": "PUT",
    "IsController": true,
    "Order": 0,
    "Parameters": [
      {
        "Name": "id",
        "Type": "System.Int32",
        "IsRequired": true
      },
      {
        "Name": "requestDTO",
        "Type": "BlazorCARS.HealthShield.DataObject.DTO.UserStoreUpdateDTO",
        "IsRequired": true
      }
    ],
    "ReturnTypes": [
      {
        "Type": "BlazorCARS.HealthShield.Utility.Response.APIResponse",
        "MediaTypes": [
          "text/plain",
          "application/json",
          "text/json"
        ],
        "StatusCode": 200
      },
      {
        "Type": "Microsoft.AspNetCore.Mvc.ProblemDetails",
        "MediaTypes": [
          "text/plain",
          "application/json",
          "text/json"
        ],
        "StatusCode": 404
      },
      {
        "Type": "System.Void",
        "MediaTypes": [],
        "StatusCode": 500
      },
      {
        "Type": "Microsoft.AspNetCore.Mvc.ProblemDetails",
        "MediaTypes": [
          "text/plain",
          "application/json",
          "text/json"
        ],
        "StatusCode": 400
      }
    ]
  },
  {
    "ContainingType": "BlazorCARS.HealthShield.WebAPI.Controllers.UserStoreController",
    "Method": "DeleteAync",
    "RelativePath": "api/userstories/{id}/{DeletedUser}",
    "HttpMethod": "DELETE",
    "IsController": true,
    "Order": 0,
    "Parameters": [
      {
        "Name": "id",
        "Type": "System.Int32",
        "IsRequired": true
      },
      {
        "Name": "DeletedUser",
        "Type": "System.String",
        "IsRequired": true
      }
    ],
    "ReturnTypes": [
      {
        "Type": "System.Void",
        "MediaTypes": [],
        "StatusCode": 500
      },
      {
        "Type": "Microsoft.AspNetCore.Mvc.ProblemDetails",
        "MediaTypes": [
          "text/plain",
          "application/json",
          "text/json"
        ],
        "StatusCode": 400
      },
      {
        "Type": "System.Void",
        "MediaTypes": [],
        "StatusCode": 204
      },
      {
        "Type": "Microsoft.AspNetCore.Mvc.ProblemDetails",
        "MediaTypes": [
          "text/plain",
          "application/json",
          "text/json"
        ],
        "StatusCode": 404
      }
    ]
  },
  {
    "ContainingType": "BlazorCARS.HealthShield.WebAPI.Controllers.UserStoreController",
    "Method": "ChangePasswordAsync",
    "RelativePath": "api/userstories/changepassword",
    "HttpMethod": "PUT",
    "IsController": true,
    "Order": 0,
    "Parameters": [
      {
        "Name": "changePasswordDTO",
        "Type": "BlazorCARS.HealthShield.DataObject.DTO.ChangePasswordDTO",
        "IsRequired": true
      }
    ],
    "ReturnTypes": [
      {
        "Type": "BlazorCARS.HealthShield.Utility.Response.APIResponse",
        "MediaTypes": [
          "text/plain",
          "application/json",
          "text/json"
        ],
        "StatusCode": 200
      },
      {
        "Type": "Microsoft.AspNetCore.Mvc.ProblemDetails",
        "MediaTypes": [
          "text/plain",
          "application/json",
          "text/json"
        ],
        "StatusCode": 400
      }
    ]
  },
  {
    "ContainingType": "BlazorCARS.HealthShield.WebAPI.Controllers.UserStoreController",
    "Method": "ResetPasswordAsync",
    "RelativePath": "api/userstories/resetpassword",
    "HttpMethod": "PUT",
    "IsController": true,
    "Order": 0,
    "Parameters": [
      {
        "Name": "resetPasswordDTO",
        "Type": "BlazorCARS.HealthShield.DataObject.DTO.ResetPasswordDTO",
        "IsRequired": true
      }
    ],
    "ReturnTypes": [
      {
        "Type": "BlazorCARS.HealthShield.Utility.Response.APIResponse",
        "MediaTypes": [
          "text/plain",
          "application/json",
          "text/json"
        ],
        "StatusCode": 200
      },
      {
        "Type": "Microsoft.AspNetCore.Mvc.ProblemDetails",
        "MediaTypes": [
          "text/plain",
          "application/json",
          "text/json"
        ],
        "StatusCode": 400
      }
    ]
  },
  {
    "ContainingType": "BlazorCARS.HealthShield.WebAPI.Controllers.VaccineRegistrationController",
    "Method": "GetAllSync",
    "RelativePath": "api/vaccineregistrations",
    "HttpMethod": "GET",
    "IsController": true,
    "Order": 0,
    "Parameters": [
      {
        "Name": "pageSize",
        "Type": "System.Int32",
        "IsRequired": false
      },
      {
        "Name": "pageNumber",
        "Type": "System.Int32",
        "IsRequired": false
      }
    ],
    "ReturnTypes": [
      {
        "Type": "BlazorCARS.HealthShield.Utility.Response.APIResponse",
        "MediaTypes": [
          "text/plain",
          "application/json",
          "text/json"
        ],
        "StatusCode": 200
      },
      {
        "Type": "Microsoft.AspNetCore.Mvc.ProblemDetails",
        "MediaTypes": [
          "text/plain",
          "application/json",
          "text/json"
        ],
        "StatusCode": 400
      },
      {
        "Type": "System.Void",
        "MediaTypes": [],
        "StatusCode": 500
      },
      {
        "Type": "Microsoft.AspNetCore.Mvc.ProblemDetails",
        "MediaTypes": [
          "text/plain",
          "application/json",
          "text/json"
        ],
        "StatusCode": 401
      }
    ]
  },
  {
    "ContainingType": "BlazorCARS.HealthShield.WebAPI.Controllers.VaccineRegistrationController",
    "Method": "CreateAsync",
    "RelativePath": "api/vaccineregistrations",
    "HttpMethod": "POST",
    "IsController": true,
    "Order": 0,
    "Parameters": [
      {
        "Name": "requestDTO",
        "Type": "BlazorCARS.HealthShield.DataObject.DTO.VaccineRegistrationCreateDTO",
        "IsRequired": true
      }
    ],
    "ReturnTypes": [
      {
        "Type": "BlazorCARS.HealthShield.Utility.Response.APIResponse",
        "MediaTypes": [
          "text/plain",
          "application/json",
          "text/json"
        ],
        "StatusCode": 201
      },
      {
        "Type": "Microsoft.AspNetCore.Mvc.ProblemDetails",
        "MediaTypes": [
          "text/plain",
          "application/json",
          "text/json"
        ],
        "StatusCode": 400
      },
      {
        "Type": "System.Void",
        "MediaTypes": [],
        "StatusCode": 500
      }
    ]
  },
  {
    "ContainingType": "BlazorCARS.HealthShield.WebAPI.Controllers.VaccineRegistrationController",
    "Method": "GetByIdAsync",
    "RelativePath": "api/vaccineregistrations/{id}",
    "HttpMethod": "GET",
    "IsController": true,
    "Order": 0,
    "Parameters": [
      {
        "Name": "id",
        "Type": "System.Int32",
        "IsRequired": true
      }
    ],
    "ReturnTypes": [
      {
        "Type": "Microsoft.AspNetCore.Mvc.ProblemDetails",
        "MediaTypes": [
          "text/plain",
          "application/json",
          "text/json"
        ],
        "StatusCode": 400
      },
      {
        "Type": "Microsoft.AspNetCore.Mvc.ProblemDetails",
        "MediaTypes": [
          "text/plain",
          "application/json",
          "text/json"
        ],
        "StatusCode": 404
      },
      {
        "Type": "BlazorCARS.HealthShield.Utility.Response.APIResponse",
        "MediaTypes": [
          "text/plain",
          "application/json",
          "text/json"
        ],
        "StatusCode": 200
      },
      {
        "Type": "System.Void",
        "MediaTypes": [],
        "StatusCode": 500
      }
    ]
  },
  {
    "ContainingType": "BlazorCARS.HealthShield.WebAPI.Controllers.VaccineRegistrationController",
    "Method": "UpdateAsync",
    "RelativePath": "api/vaccineregistrations/{id}",
    "HttpMethod": "PUT",
    "IsController": true,
    "Order": 0,
    "Parameters": [
      {
        "Name": "id",
        "Type": "System.Int32",
        "IsRequired": true
      },
      {
        "Name": "requestDTO",
        "Type": "BlazorCARS.HealthShield.DataObject.DTO.VaccineRegistrationUpdateDTO",
        "IsRequired": true
      }
    ],
    "ReturnTypes": [
      {
        "Type": "BlazorCARS.HealthShield.Utility.Response.APIResponse",
        "MediaTypes": [
          "text/plain",
          "application/json",
          "text/json"
        ],
        "StatusCode": 200
      },
      {
        "Type": "Microsoft.AspNetCore.Mvc.ProblemDetails",
        "MediaTypes": [
          "text/plain",
          "application/json",
          "text/json"
        ],
        "StatusCode": 404
      },
      {
        "Type": "System.Void",
        "MediaTypes": [],
        "StatusCode": 500
      },
      {
        "Type": "Microsoft.AspNetCore.Mvc.ProblemDetails",
        "MediaTypes": [
          "text/plain",
          "application/json",
          "text/json"
        ],
        "StatusCode": 400
      }
    ]
  },
  {
    "ContainingType": "BlazorCARS.HealthShield.WebAPI.Controllers.VaccineRegistrationController",
    "Method": "DeleteAync",
    "RelativePath": "api/vaccineregistrations/{id}",
    "HttpMethod": "DELETE",
    "IsController": true,
    "Order": 0,
    "Parameters": [
      {
        "Name": "id",
        "Type": "System.Int32",
        "IsRequired": true
      }
    ],
    "ReturnTypes": [
      {
        "Type": "System.Void",
        "MediaTypes": [],
        "StatusCode": 500
      },
      {
        "Type": "Microsoft.AspNetCore.Mvc.ProblemDetails",
        "MediaTypes": [
          "text/plain",
          "application/json",
          "text/json"
        ],
        "StatusCode": 400
      },
      {
        "Type": "System.Void",
        "MediaTypes": [],
        "StatusCode": 204
      },
      {
        "Type": "Microsoft.AspNetCore.Mvc.ProblemDetails",
        "MediaTypes": [
          "text/plain",
          "application/json",
          "text/json"
        ],
        "StatusCode": 404
      }
    ]
  },
  {
    "ContainingType": "BlazorCARS.HealthShield.WebAPI.Controllers.VaccineRegistrationController",
    "Method": "GetActiveappoinmentAsync",
    "RelativePath": "api/vaccineregistrations/active/{id}",
    "HttpMethod": "GET",
    "IsController": true,
    "Order": 0,
    "Parameters": [
      {
        "Name": "id",
        "Type": "System.Int32",
        "IsRequired": true
      }
    ],
    "ReturnTypes": [
      {
        "Type": "BlazorCARS.HealthShield.Utility.Response.APIResponse",
        "MediaTypes": [
          "text/plain",
          "application/json",
          "text/json"
        ],
        "StatusCode": 200
      },
      {
        "Type": "Microsoft.AspNetCore.Mvc.ProblemDetails",
        "MediaTypes": [
          "text/plain",
          "application/json",
          "text/json"
        ],
        "StatusCode": 400
      },
      {
        "Type": "System.Void",
        "MediaTypes": [],
        "StatusCode": 500
      },
      {
        "Type": "Microsoft.AspNetCore.Mvc.ProblemDetails",
        "MediaTypes": [
          "text/plain",
          "application/json",
          "text/json"
        ],
        "StatusCode": 401
      }
    ]
  },
  {
    "ContainingType": "BlazorCARS.HealthShield.WebAPI.Controllers.VaccineRegistrationController",
    "Method": "GetActiveappoinmentByHospitalAsync",
    "RelativePath": "api/vaccineregistrations/hospitalactiveappointment/{id}",
    "HttpMethod": "GET",
    "IsController": true,
    "Order": 0,
    "Parameters": [
      {
        "Name": "id",
        "Type": "System.Int32",
        "IsRequired": true
      }
    ],
    "ReturnTypes": [
      {
        "Type": "BlazorCARS.HealthShield.Utility.Response.APIResponse",
        "MediaTypes": [
          "text/plain",
          "application/json",
          "text/json"
        ],
        "StatusCode": 200
      },
      {
        "Type": "Microsoft.AspNetCore.Mvc.ProblemDetails",
        "MediaTypes": [
          "text/plain",
          "application/json",
          "text/json"
        ],
        "StatusCode": 400
      },
      {
        "Type": "System.Void",
        "MediaTypes": [],
        "StatusCode": 500
      },
      {
        "Type": "Microsoft.AspNetCore.Mvc.ProblemDetails",
        "MediaTypes": [
          "text/plain",
          "application/json",
          "text/json"
        ],
        "StatusCode": 401
      }
    ]
  },
  {
    "ContainingType": "BlazorCARS.HealthShield.WebAPI.Controllers.VaccineController",
    "Method": "GetAllAsync",
    "RelativePath": "api/vaccines",
    "HttpMethod": "GET",
    "IsController": true,
    "Order": 0,
    "Parameters": [
      {
        "Name": "pageSize",
        "Type": "System.Int32",
        "IsRequired": false
      },
      {
        "Name": "pageNumber",
        "Type": "System.Int32",
        "IsRequired": false
      }
    ],
    "ReturnTypes": [
      {
        "Type": "BlazorCARS.HealthShield.Utility.Response.APIResponse",
        "MediaTypes": [
          "text/plain",
          "application/json",
          "text/json"
        ],
        "StatusCode": 200
      },
      {
        "Type": "Microsoft.AspNetCore.Mvc.ProblemDetails",
        "MediaTypes": [
          "text/plain",
          "application/json",
          "text/json"
        ],
        "StatusCode": 400
      },
      {
        "Type": "System.Void",
        "MediaTypes": [],
        "StatusCode": 500
      },
      {
        "Type": "Microsoft.AspNetCore.Mvc.ProblemDetails",
        "MediaTypes": [
          "text/plain",
          "application/json",
          "text/json"
        ],
        "StatusCode": 401
      }
    ]
  },
  {
    "ContainingType": "BlazorCARS.HealthShield.WebAPI.Controllers.VaccineController",
    "Method": "CreateAsync",
    "RelativePath": "api/vaccines",
    "HttpMethod": "POST",
    "IsController": true,
    "Order": 0,
    "Parameters": [
      {
        "Name": "requestDTO",
        "Type": "BlazorCARS.HealthShield.DataObject.DTO.VaccineCreateDTO",
        "IsRequired": true
      }
    ],
    "ReturnTypes": [
      {
        "Type": "BlazorCARS.HealthShield.Utility.Response.APIResponse",
        "MediaTypes": [
          "text/plain",
          "application/json",
          "text/json"
        ],
        "StatusCode": 201
      },
      {
        "Type": "Microsoft.AspNetCore.Mvc.ProblemDetails",
        "MediaTypes": [
          "text/plain",
          "application/json",
          "text/json"
        ],
        "StatusCode": 400
      },
      {
        "Type": "System.Void",
        "MediaTypes": [],
        "StatusCode": 500
      }
    ]
  },
  {
    "ContainingType": "BlazorCARS.HealthShield.WebAPI.Controllers.VaccineController",
    "Method": "GetByIdAsync",
    "RelativePath": "api/vaccines/{id}",
    "HttpMethod": "GET",
    "IsController": true,
    "Order": 0,
    "Parameters": [
      {
        "Name": "id",
        "Type": "System.Int32",
        "IsRequired": true
      }
    ],
    "ReturnTypes": [
      {
        "Type": "Microsoft.AspNetCore.Mvc.ProblemDetails",
        "MediaTypes": [
          "text/plain",
          "application/json",
          "text/json"
        ],
        "StatusCode": 400
      },
      {
        "Type": "Microsoft.AspNetCore.Mvc.ProblemDetails",
        "MediaTypes": [
          "text/plain",
          "application/json",
          "text/json"
        ],
        "StatusCode": 404
      },
      {
        "Type": "BlazorCARS.HealthShield.Utility.Response.APIResponse",
        "MediaTypes": [
          "text/plain",
          "application/json",
          "text/json"
        ],
        "StatusCode": 200
      },
      {
        "Type": "System.Void",
        "MediaTypes": [],
        "StatusCode": 500
      }
    ]
  },
  {
    "ContainingType": "BlazorCARS.HealthShield.WebAPI.Controllers.VaccineController",
    "Method": "UpdateAsync",
    "RelativePath": "api/vaccines/{id}",
    "HttpMethod": "PUT",
    "IsController": true,
    "Order": 0,
    "Parameters": [
      {
        "Name": "id",
        "Type": "System.Int32",
        "IsRequired": true
      },
      {
        "Name": "requestDTO",
        "Type": "BlazorCARS.HealthShield.DataObject.DTO.VaccineUpdateDTO",
        "IsRequired": true
      }
    ],
    "ReturnTypes": [
      {
        "Type": "BlazorCARS.HealthShield.Utility.Response.APIResponse",
        "MediaTypes": [
          "text/plain",
          "application/json",
          "text/json"
        ],
        "StatusCode": 200
      },
      {
        "Type": "Microsoft.AspNetCore.Mvc.ProblemDetails",
        "MediaTypes": [
          "text/plain",
          "application/json",
          "text/json"
        ],
        "StatusCode": 404
      },
      {
        "Type": "System.Void",
        "MediaTypes": [],
        "StatusCode": 500
      },
      {
        "Type": "Microsoft.AspNetCore.Mvc.ProblemDetails",
        "MediaTypes": [
          "text/plain",
          "application/json",
          "text/json"
        ],
        "StatusCode": 400
      }
    ]
  },
  {
    "ContainingType": "BlazorCARS.HealthShield.WebAPI.Controllers.VaccineController",
    "Method": "DeleteAync",
    "RelativePath": "api/vaccines/{id}/{DeletedUser}",
    "HttpMethod": "DELETE",
    "IsController": true,
    "Order": 0,
    "Parameters": [
      {
        "Name": "id",
        "Type": "System.Int32",
        "IsRequired": true
      },
      {
        "Name": "DeletedUser",
        "Type": "System.String",
        "IsRequired": true
      }
    ],
    "ReturnTypes": [
      {
        "Type": "System.Void",
        "MediaTypes": [],
        "StatusCode": 500
      },
      {
        "Type": "Microsoft.AspNetCore.Mvc.ProblemDetails",
        "MediaTypes": [
          "text/plain",
          "application/json",
          "text/json"
        ],
        "StatusCode": 400
      },
      {
        "Type": "System.Void",
        "MediaTypes": [],
        "StatusCode": 204
      },
      {
        "Type": "Microsoft.AspNetCore.Mvc.ProblemDetails",
        "MediaTypes": [
          "text/plain",
          "application/json",
          "text/json"
        ],
        "StatusCode": 404
      }
    ]
  },
  {
    "ContainingType": "BlazorCARS.HealthShield.WebAPI.Controllers.VaccineScheduleController",
    "Method": "GetAllSync",
    "RelativePath": "api/vaccineschedules",
    "HttpMethod": "GET",
    "IsController": true,
    "Order": 0,
    "Parameters": [
      {
        "Name": "pageSize",
        "Type": "System.Int32",
        "IsRequired": false
      },
      {
        "Name": "pageNumber",
        "Type": "System.Int32",
        "IsRequired": false
      }
    ],
    "ReturnTypes": [
      {
        "Type": "BlazorCARS.HealthShield.Utility.Response.APIResponse",
        "MediaTypes": [
          "text/plain",
          "application/json",
          "text/json"
        ],
        "StatusCode": 200
      }
    ]
  },
  {
    "ContainingType": "BlazorCARS.HealthShield.WebAPI.Controllers.VaccineScheduleController",
    "Method": "CreateAsync",
    "RelativePath": "api/vaccineschedules",
    "HttpMethod": "POST",
    "IsController": true,
    "Order": 0,
    "Parameters": [
      {
        "Name": "requestDTO",
        "Type": "BlazorCARS.HealthShield.DataObject.DTO.VaccineScheduleCreateDTO",
        "IsRequired": true
      }
    ],
    "ReturnTypes": [
      {
        "Type": "BlazorCARS.HealthShield.Utility.Response.APIResponse",
        "MediaTypes": [
          "text/plain",
          "application/json",
          "text/json"
        ],
        "StatusCode": 201
      },
      {
        "Type": "Microsoft.AspNetCore.Mvc.ProblemDetails",
        "MediaTypes": [
          "text/plain",
          "application/json",
          "text/json"
        ],
        "StatusCode": 400
      },
      {
        "Type": "System.Void",
        "MediaTypes": [],
        "StatusCode": 500
      }
    ]
  },
  {
    "ContainingType": "BlazorCARS.HealthShield.WebAPI.Controllers.VaccineScheduleController",
    "Method": "GetByIdAsync",
    "RelativePath": "api/vaccineschedules/{id}",
    "HttpMethod": "GET",
    "IsController": true,
    "Order": 0,
    "Parameters": [
      {
        "Name": "id",
        "Type": "System.Int32",
        "IsRequired": true
      }
    ],
    "ReturnTypes": [
      {
        "Type": "Microsoft.AspNetCore.Mvc.ProblemDetails",
        "MediaTypes": [
          "text/plain",
          "application/json",
          "text/json"
        ],
        "StatusCode": 400
      },
      {
        "Type": "Microsoft.AspNetCore.Mvc.ProblemDetails",
        "MediaTypes": [
          "text/plain",
          "application/json",
          "text/json"
        ],
        "StatusCode": 404
      },
      {
        "Type": "BlazorCARS.HealthShield.Utility.Response.APIResponse",
        "MediaTypes": [
          "text/plain",
          "application/json",
          "text/json"
        ],
        "StatusCode": 200
      },
      {
        "Type": "System.Void",
        "MediaTypes": [],
        "StatusCode": 500
      }
    ]
  },
  {
    "ContainingType": "BlazorCARS.HealthShield.WebAPI.Controllers.VaccineScheduleController",
    "Method": "UpdateAsync",
    "RelativePath": "api/vaccineschedules/{id}",
    "HttpMethod": "PUT",
    "IsController": true,
    "Order": 0,
    "Parameters": [
      {
        "Name": "id",
        "Type": "System.Int32",
        "IsRequired": true
      },
      {
        "Name": "requestDTO",
        "Type": "BlazorCARS.HealthShield.DataObject.DTO.VaccineScheduleUpdateDTO",
        "IsRequired": true
      }
    ],
    "ReturnTypes": [
      {
        "Type": "BlazorCARS.HealthShield.Utility.Response.APIResponse",
        "MediaTypes": [
          "text/plain",
          "application/json",
          "text/json"
        ],
        "StatusCode": 200
      },
      {
        "Type": "Microsoft.AspNetCore.Mvc.ProblemDetails",
        "MediaTypes": [
          "text/plain",
          "application/json",
          "text/json"
        ],
        "StatusCode": 404
      },
      {
        "Type": "System.Void",
        "MediaTypes": [],
        "StatusCode": 500
      },
      {
        "Type": "Microsoft.AspNetCore.Mvc.ProblemDetails",
        "MediaTypes": [
          "text/plain",
          "application/json",
          "text/json"
        ],
        "StatusCode": 400
      }
    ]
  },
  {
    "ContainingType": "BlazorCARS.HealthShield.WebAPI.Controllers.VaccineScheduleController",
    "Method": "DeleteAync",
    "RelativePath": "api/vaccineschedules/{id}",
    "HttpMethod": "DELETE",
    "IsController": true,
    "Order": 0,
    "Parameters": [
      {
        "Name": "id",
        "Type": "System.Int32",
        "IsRequired": true
      }
    ],
    "ReturnTypes": [
      {
        "Type": "System.Void",
        "MediaTypes": [],
        "StatusCode": 500
      },
      {
        "Type": "Microsoft.AspNetCore.Mvc.ProblemDetails",
        "MediaTypes": [
          "text/plain",
          "application/json",
          "text/json"
        ],
        "StatusCode": 400
      },
      {
        "Type": "System.Void",
        "MediaTypes": [],
        "StatusCode": 204
      },
      {
        "Type": "Microsoft.AspNetCore.Mvc.ProblemDetails",
        "MediaTypes": [
          "text/plain",
          "application/json",
          "text/json"
        ],
        "StatusCode": 404
      }
    ]
  }
]